MANIFEST.in
setup.py
docs/AUTHORS
docs/Changelog
docs/FAQ
docs/INSTALL
docs/LICENSE
docs/NEWS
docs/README
docs/THANKS
docs/TODO
examples/atom.py
examples/blog.py
examples/hcard.py
shrubbery/__init__.py
shrubbery/buffet.py
shrubbery/template.py
shrubbery.egg-info/PKG-INFO
shrubbery.egg-info/SOURCES.txt
shrubbery.egg-info/dependency_links.txt
shrubbery.egg-info/entry_points.txt
shrubbery.egg-info/requires.txt
shrubbery.egg-info/top_level.txt
shrubbery.egg-info/zip-safe
tests/test_basic.py
