Metadata-Version: 1.0
Name: shrubbery
Version: 0.3.3
Summary: Simple and smart template engine to generate HTML/XML
Home-page: http://taoetc.org/46
Author: Roberto De Almeida
Author-email: roberto@dealmeida.net
License: MIT
Download-URL: http://cheeseshop.python.org/packages/source/s/shrubbery/shrubbery-0.3.3.tar.gz
Keywords: json template html xml
Platform: UNKNOWN
Classifier: Development Status :: 4 - Beta
Classifier: Intended Audience :: Developers
Classifier: License :: OSI Approved :: MIT License
Classifier: Operating System :: OS Independent
Classifier: Programming Language :: Python
Classifier: Topic :: Text Processing :: Markup
